{
  "hash": "1e6e28850e3f40c692f6b20168b942f2",
  "result": {
    "engine": "knitr",
    "markdown": "---\ntitle: \"West Texas\"\nsubtitle: \"Regional economy — Sonora, Eldorado, Ozona, and Junction vs. Texas and the US\"\n---\n\n\n\n\n\n\nA comparison of the West Texas regional economy to the state of Texas and\nthe United States, focusing on four small towns in the Edwards Plateau and\nPermian Basin fringe:\n\n- **Sonora** (Sutton County, pop. ~3,000)\n- **Eldorado** (Schleicher County, pop. ~2,800)\n- **Ozona** (Crockett County, pop. ~3,400)\n- **Junction** (Kimble County, pop. ~4,400)\n\nThese communities share an economy shaped by ranching, oil and gas services,\nand highway commerce. County-level data from the Bureau of Labor Statistics\nand Bureau of Economic Analysis allows direct comparison to state and\nnational benchmarks.\n\n\n\n\n::: {.cell}\n::: {.cell-output-display}\n\n```{=html}\n<div style=\"display:flex; flex-wrap: wrap; gap: 12px; margin: 10px 0 20px;\">\n<div style=\"border: 1px solid #dee2e6; border-radius: 8px; padding: 14px 16px;&#10;       background: #fff; box-shadow: 0 1px 2px rgba(0,0,0,0.03);&#10;       min-width: 170px; flex: 1;\">\n<div style=\"font-size: 0.80rem; color:#6c757d; letter-spacing: .02em; text-transform: uppercase;\">US Unemployment</div>\n<div style=\"font-size: 1.7rem; font-weight: 600; color: #1d3557; line-height: 1.15; margin-top: 4px;\">4.3%</div>\n<div style=\"font-size: 0.82rem; color:#6c757d; margin-top: 2px;\">Latest month, BLS</div>\n</div>\n<div style=\"border: 1px solid #dee2e6; border-radius: 8px; padding: 14px 16px;&#10;       background: #fff; box-shadow: 0 1px 2px rgba(0,0,0,0.03);&#10;       min-width: 170px; flex: 1;\">\n<div style=\"font-size: 0.80rem; color:#6c757d; letter-spacing: .02em; text-transform: uppercase;\">Texas Unemployment</div>\n<div style=\"font-size: 1.7rem; font-weight: 600; color: #1d3557; line-height: 1.15; margin-top: 4px;\">4.3%</div>\n<div style=\"font-size: 0.82rem; color:#6c757d; margin-top: 2px;\">Latest month, BLS</div>\n</div>\n<div style=\"border: 1px solid #dee2e6; border-radius: 8px; padding: 14px 16px;&#10;       background: #fff; box-shadow: 0 1px 2px rgba(0,0,0,0.03);&#10;       min-width: 170px; flex: 1;\">\n<div style=\"font-size: 0.80rem; color:#6c757d; letter-spacing: .02em; text-transform: uppercase;\">West TX Region</div>\n<div style=\"font-size: 1.7rem; font-weight: 600; color: #1d3557; line-height: 1.15; margin-top: 4px;\">4.7%</div>\n<div style=\"font-size: 0.82rem; color:#6c757d; margin-top: 2px;\">Avg of 4 counties</div>\n</div>\n<div style=\"border: 1px solid #dee2e6; border-radius: 8px; padding: 14px 16px;&#10;       background: #fff; box-shadow: 0 1px 2px rgba(0,0,0,0.03);&#10;       min-width: 170px; flex: 1;\">\n<div style=\"font-size: 0.80rem; color:#6c757d; letter-spacing: .02em; text-transform: uppercase;\">Regional Spread</div>\n<div style=\"font-size: 1.7rem; font-weight: 600; color: #bc4749; line-height: 1.15; margin-top: 4px;\">+0.4%</div>\n<div style=\"font-size: 0.82rem; color:#6c757d; margin-top: 2px;\">Region vs. US</div>\n</div>\n</div>\n```\n\n:::\n:::\n\n::: {.cell}\n::: {.cell-output-display}\n\n```{=html}\n<div style=\"display:flex; flex-wrap: wrap; gap: 12px; margin: 10px 0 20px;\">\n<div style=\"border: 1px solid #dee2e6; border-radius: 8px; padding: 14px 16px;&#10;       background: #fff; box-shadow: 0 1px 2px rgba(0,0,0,0.03);&#10;       min-width: 170px; flex: 1;\">\n<div style=\"font-size: 0.80rem; color:#6c757d; letter-spacing: .02em; text-transform: uppercase;\">US Per-Capita Income</div>\n<div style=\"font-size: 1.7rem; font-weight: 600; color: #1d3557; line-height: 1.15; margin-top: 4px;\">$73,204</div>\n<div style=\"font-size: 0.82rem; color:#6c757d; margin-top: 2px;\">Latest year, BEA</div>\n</div>\n<div style=\"border: 1px solid #dee2e6; border-radius: 8px; padding: 14px 16px;&#10;       background: #fff; box-shadow: 0 1px 2px rgba(0,0,0,0.03);&#10;       min-width: 170px; flex: 1;\">\n<div style=\"font-size: 0.80rem; color:#6c757d; letter-spacing: .02em; text-transform: uppercase;\">Texas Per-Capita Income</div>\n<div style=\"font-size: 1.7rem; font-weight: 600; color: #1d3557; line-height: 1.15; margin-top: 4px;\">$69,823</div>\n<div style=\"font-size: 0.82rem; color:#6c757d; margin-top: 2px;\">Latest year, BEA</div>\n</div>\n<div style=\"border: 1px solid #dee2e6; border-radius: 8px; padding: 14px 16px;&#10;       background: #fff; box-shadow: 0 1px 2px rgba(0,0,0,0.03);&#10;       min-width: 170px; flex: 1;\">\n<div style=\"font-size: 0.80rem; color:#6c757d; letter-spacing: .02em; text-transform: uppercase;\">West TX Region</div>\n<div style=\"font-size: 1.7rem; font-weight: 600; color: #1d3557; line-height: 1.15; margin-top: 4px;\">$65,924</div>\n<div style=\"font-size: 0.82rem; color:#6c757d; margin-top: 2px;\">Avg of 4 counties</div>\n</div>\n</div>\n```\n\n:::\n:::\n\n\n\n\n## Sections\n\n- **[Unemployment →](unemployment.qmd)** — Monthly unemployment rates for\n  each county vs. Texas and the US, from 2005 to present.\n- **[Per-Capita Income →](income.qmd)** — Annual per-capita personal income\n  by county, with comparisons to state and national averages.\n- **[Economic Output →](gdp.qmd)** — Annual GDP for Texas and the US, with\n  county-level output where available from the BEA.\n- **[Methodology →](about.qmd)** — Data sources, FIPS codes, population\n  context, and caveats about small-county volatility.\n\n## Data sources\n\n| Source | What | License | Refresh |\n|---|---|---|---|\n| [BLS LAUS](https://www.bls.gov/lau/) | Monthly county unemployment rates | Public domain (US gov) | Monthly |\n| [BEA Regional](https://www.bea.gov/data/by-place-county-metro-local) | Annual county GDP and per-capita income | Public domain (US gov) | Annual (~6 mo lag) |\n| [FRED](https://fred.stlouisfed.org/) | US unemployment (UNRATE), Texas unemployment (TXUR), Texas real GSP (TXRGSP) | Public domain | Daily / monthly |\n",
    "supporting": [],
    "filters": [
      "rmarkdown/pagebreak.lua"
    ],
    "includes": {},
    "engineDependencies": {},
    "preserve": {},
    "postProcess": true
  }
}